{"mdph.beta.gouv.fr":{"inspect":{"Domain":"mdph.beta.gouv.fr","Base Domain":"gouv.fr","Canonical":"https://mdph.beta.gouv.fr","Live":true,"Redirect":false,"Redirect To":"","Valid HTTPS":true,"Defaults to HTTPS":true,"Downgrades HTTPS":false,"Strictly Forces HTTPS":true,"HTTPS Bad Chain":false,"HTTPS Bad Hostname":false,"HSTS":true,"HSTS Header":"max-age=31536000; includeSubDomains; preload","HSTS Max Age":"31536000","HSTS All Subdomains":true,"HSTS Preload Ready":true,"HSTS Preloaded":false,"Broken Root":false,"Broken WWW":true},"sslyze":{"Domain":"mdph.beta.gouv.fr","Base Domain":"gouv.fr","SSLv2":false,"SSLv3":false,"TLSv1.0":true,"TLSv1.1":true,"TLSv1.2":true,"Any Forward Secrecy":true,"All Forward Secrecy":false,"Weakest DH Group Size":"2048","Any RC4":false,"All RC4":false,"OCSP Stapling":false,"Key Type":"rsaEncryption","Key Length":"2048","Signature Algorithm":"sha256WithRSAEncryption","SHA-1 in Served Chain":false,"Not Before":"2016-04-01 13:07:24+00:00","Not After":"2017-04-01 13:07:24+00:00","Highest Served Issuer":"StartCom Certification Authority","Errors":""},"tls":{"Domain":"mdph.beta.gouv.fr","Base Domain":"gouv.fr","Grade":"A+","Signature Algorithm":"SHA256withRSA","Key Type":"RSA","Key Size":"2048","Forward Secrecy":"4","OCSP Stapling":false,"Fallback SCSV":true,"RC4":false,"SSLv3":false,"TLSv1.2":true,"SPDY":false,"Requires SNI":false,"HTTP/2":false},"pageload":{"Domain":"mdph.beta.gouv.fr","Base Domain":"gouv.fr","requests":"17","httpsRequests":"17","timeToFirstByte":"121","timeToLastByte":"133","httpTrafficCompleted":"719","domContentLoaded":"276","domComplete":"600","timeBackend":"17","timeFrontend":"83"},"meta":{"Domain":"mdph.beta.gouv.fr"," Administration":" Incubateur Services Numeriques"," Type":" website"}},"mes-aides.gouv.fr":{"inspect":{"Domain":"mes-aides.gouv.fr","Base Domain":"gouv.fr","Canonical":"https://mes-aides.gouv.fr","Live":true,"Redirect":false,"Redirect To":"","Valid HTTPS":true,"Defaults to HTTPS":true,"Downgrades HTTPS":false,"Strictly Forces HTTPS":true,"HTTPS Bad Chain":false,"HTTPS Bad Hostname":false,"HSTS":false,"HSTS Header":"","HSTS Max Age":"","HSTS All Subdomains":false,"HSTS Preload Ready":false,"HSTS Preloaded":false,"Broken Root":false,"Broken WWW":false},"sslyze":{"Domain":"mes-aides.gouv.fr","Base Domain":"gouv.fr","SSLv2":false,"SSLv3":false,"TLSv1.0":true,"TLSv1.1":true,"TLSv1.2":true,"Any Forward Secrecy":true,"All Forward Secrecy":true,"Weakest DH Group Size":"2048","Any RC4":false,"All RC4":false,"OCSP Stapling":false,"Key Type":"rsaEncryption","Key Length":"2048","Signature Algorithm":"sha256WithRSAEncryption","SHA-1 in Served Chain":true,"Not Before":"2015-01-27 00:00:00+00:00","Not After":"2017-01-26 23:59:59+00:00","Highest Served Issuer":"Thawte Premium Server CA","Errors":""},"tls":{"Domain":"mes-aides.gouv.fr","Base Domain":"gouv.fr","Grade":"F","Signature Algorithm":"SHA256withRSA","Key Type":"RSA","Key Size":"2048","Forward Secrecy":"4","OCSP Stapling":false,"Fallback SCSV":true,"RC4":false,"SSLv3":false,"TLSv1.2":true,"SPDY":false,"Requires SNI":false,"HTTP/2":false},"pageload":{"Domain":"mes-aides.gouv.fr","Base Domain":"gouv.fr","requests":"12","httpsRequests":"12","timeToFirstByte":"114","timeToLastByte":"135","httpTrafficCompleted":"532","domContentLoaded":"322","domComplete":"420","timeBackend":"21","timeFrontend":"79"},"meta":{"Domain":"mes-aides.gouv.fr"," Administration":" Incubateur Services Numeriques"," Type":" website"}},"api.gouv.fr":{"inspect":{"Domain":"api.gouv.fr","Base Domain":"gouv.fr","Canonical":"https://api.gouv.fr","Live":true,"Redirect":false,"Redirect To":"","Valid HTTPS":true,"Defaults to HTTPS":true,"Downgrades HTTPS":false,"Strictly Forces HTTPS":true,"HTTPS Bad Chain":false,"HTTPS Bad Hostname":false,"HSTS":false,"HSTS Header":"","HSTS Max Age":"","HSTS All Subdomains":false,"HSTS Preload Ready":false,"HSTS Preloaded":false,"Broken Root":false,"Broken WWW":false},"sslyze":{"Domain":"api.gouv.fr","Base Domain":"gouv.fr","SSLv2":false,"SSLv3":false,"TLSv1.0":true,"TLSv1.1":true,"TLSv1.2":true,"Any Forward Secrecy":true,"All Forward Secrecy":false,"Weakest DH Group Size":"2048","Any RC4":false,"All RC4":false,"OCSP Stapling":false,"Key Type":"rsaEncryption","Key Length":"2048","Signature Algorithm":"sha256WithRSAEncryption","SHA-1 in Served Chain":false,"Not Before":"2016-03-17 14:11:28+00:00","Not After":"2017-03-17 14:11:28+00:00","Highest Served Issuer":"StartCom Certification Authority","Errors":""},"tls":{"Domain":"api.gouv.fr","Base Domain":"gouv.fr","Grade":"A","Signature Algorithm":"SHA256withRSA","Key Type":"RSA","Key Size":"2048","Forward Secrecy":"4","OCSP Stapling":false,"Fallback SCSV":true,"RC4":false,"SSLv3":false,"TLSv1.2":true,"SPDY":false,"Requires SNI":true,"HTTP/2":false},"pageload":{"Domain":"api.gouv.fr","Base Domain":"gouv.fr","requests":"46","httpsRequests":"46","timeToFirstByte":"127","timeToLastByte":"154","httpTrafficCompleted":"931","domContentLoaded":"399","domComplete":"781","timeBackend":"14","timeFrontend":"86"},"meta":{"Domain":"api.gouv.fr"," Administration":" DINSIC"," Type":" website"}},"beta.gouv.fr":{"inspect":{"Domain":"beta.gouv.fr","Base Domain":"gouv.fr","Canonical":"https://beta.gouv.fr","Live":true,"Redirect":false,"Redirect To":"","Valid HTTPS":true,"Defaults to HTTPS":true,"Downgrades HTTPS":false,"Strictly Forces HTTPS":true,"HTTPS Bad Chain":false,"HTTPS Bad Hostname":false,"HSTS":false,"HSTS Header":"","HSTS Max Age":"","HSTS All Subdomains":false,"HSTS Preload Ready":false,"HSTS Preloaded":false,"Broken Root":false,"Broken WWW":false},"sslyze":{"Domain":"beta.gouv.fr","Base Domain":"gouv.fr","SSLv2":false,"SSLv3":false,"TLSv1.0":true,"TLSv1.1":true,"TLSv1.2":true,"Any Forward Secrecy":true,"All Forward Secrecy":false,"Weakest DH Group Size":"2048","Any RC4":false,"All RC4":false,"OCSP Stapling":false,"Key Type":"rsaEncryption","Key Length":"2048","Signature Algorithm":"sha256WithRSAEncryption","SHA-1 in Served Chain":false,"Not Before":"2016-02-25 13:47:00+00:00","Not After":"2017-02-25 13:47:00+00:00","Highest Served Issuer":"StartCom Certification Authority","Errors":""},"tls":{"Domain":"beta.gouv.fr","Base Domain":"gouv.fr","Grade":"A","Signature Algorithm":"SHA256withRSA","Key Type":"RSA","Key Size":"2048","Forward Secrecy":"4","OCSP Stapling":false,"Fallback SCSV":true,"RC4":false,"SSLv3":false,"TLSv1.2":true,"SPDY":false,"Requires SNI":true,"HTTP/2":false},"pageload":{"Domain":"beta.gouv.fr","Base Domain":"gouv.fr","requests":"33","httpsRequests":"33","timeToFirstByte":"263","timeToLastByte":"291","httpTrafficCompleted":"1006","domContentLoaded":"425","domComplete":"724","timeBackend":"27","timeFrontend":"73"},"meta":{"Domain":"beta.gouv.fr"," Administration":" Incubateur Services Numeriques"," Type":" website"}},"geo.api.gouv.fr":{"inspect":{"Domain":"geo.api.gouv.fr","Base Domain":"gouv.fr","Canonical":"https://geo.api.gouv.fr","Live":true,"Redirect":false,"Redirect To":"","Valid HTTPS":true,"Defaults to HTTPS":true,"Downgrades HTTPS":false,"Strictly Forces HTTPS":true,"HTTPS Bad Chain":false,"HTTPS Bad Hostname":false,"HSTS":false,"HSTS Header":"","HSTS Max Age":"","HSTS All Subdomains":false,"HSTS Preload Ready":false,"HSTS Preloaded":false,"Broken Root":false,"Broken WWW":true},"sslyze":{"Domain":"geo.api.gouv.fr","Base Domain":"gouv.fr","SSLv2":false,"SSLv3":false,"TLSv1.0":true,"TLSv1.1":true,"TLSv1.2":true,"Any Forward Secrecy":true,"All Forward Secrecy":false,"Weakest DH Group Size":"2048","Any RC4":false,"All RC4":false,"OCSP Stapling":false,"Key Type":"rsaEncryption","Key Length":"2048","Signature Algorithm":"sha256WithRSAEncryption","SHA-1 in Served Chain":false,"Not Before":"2016-05-17 19:37:59+00:00","Not After":"2017-05-17 19:37:59+00:00","Highest Served Issuer":"StartCom Certification Authority","Errors":""},"tls":{"Domain":"geo.api.gouv.fr","Base Domain":"gouv.fr","Grade":"A","Signature Algorithm":"SHA256withRSA","Key Type":"RSA","Key Size":"2048","Forward Secrecy":"4","OCSP Stapling":false,"Fallback SCSV":true,"RC4":false,"SSLv3":false,"TLSv1.2":true,"SPDY":false,"Requires SNI":false,"HTTP/2":false},"pageload":{"Domain":"geo.api.gouv.fr","Base Domain":"gouv.fr","requests":"1","httpsRequests":"1","timeToFirstByte":"188","timeToLastByte":"189","httpTrafficCompleted":"187","domContentLoaded":"0","domComplete":"0","timeBackend":"100","timeFrontend":"0"},"meta":{"Domain":"geo.api.gouv.fr"," Administration":" Incubateur Services Numeriques"," Type":" api"}},"particulier.api.gouv.fr":{"inspect":{"Domain":"particulier.api.gouv.fr","Base Domain":"gouv.fr","Canonical":"http://particulier.api.gouv.fr","Live":true,"Redirect":false,"Redirect To":"","Valid HTTPS":false,"Defaults to HTTPS":false,"Downgrades HTTPS":false,"Strictly Forces HTTPS":false,"HTTPS Bad Chain":false,"HTTPS Bad Hostname":false,"HSTS":false,"HSTS Header":"","HSTS Max Age":"","HSTS All Subdomains":false,"HSTS Preload Ready":false,"HSTS Preloaded":false,"Broken Root":false,"Broken WWW":true},"pageload":{"Domain":"particulier.api.gouv.fr","Base Domain":"gouv.fr","requests":"18","httpsRequests":"17","timeToFirstByte":"3112","timeToLastByte":"3127","httpTrafficCompleted":"3859","domContentLoaded":"128","domComplete":"387","timeBackend":"89","timeFrontend":"11"},"meta":{"Domain":"particulier.api.gouv.fr"," Administration":" Incubateur Services Numeriques"," Type":" api"}}}